ADvis/ADgraph.py
ADvis/ADmath.py
ADvis/ADnum.py
ADvis/__init__.py
ADvis-0.0.1.dist-info/LICENSE
ADvis-0.0.1.dist-info/METADATA
ADvis-0.0.1.dist-info/WHEEL
ADvis-0.0.1.dist-info/top_level.txt
ADvis-0.0.1.dist-info/RECORD
