Metadata-Version: 2.1
Name: ADvis
Version: 0.0.1
Summary: AD library for visualization to aid in the learning of automatic differentiation
Home-page: https://github.com/CS207-AD20/ADvisualizationtools
Author: Lindsey Brown, Xinyue Wang
Author-email: lindsey_brown@g.harvard.edu
License: UNKNOWN
Platform: UNKNOWN
Classifier: Programming Language :: Python :: 3
Classifier: License :: OSI Approved :: MIT License
Classifier: Operating System :: OS Independent
Requires-Python: >=3.6
